Workbook

Sheet Paramètres
B2: DEVIS — MISSION DE CONSEIL TECHNIQUE
B3: Intégration Call Com × Orange Tunisie
B5: LÉGENDE
B6: Cellules JAUNES | C6: à modifier | D6: Ce sont les seules cellules à éditer. Tout le reste est calculé.
B7: Texte bleu | D7: Saisie / hypothèse
B8: Texte noir | D8: Formule — ne pas écraser
B9: Texte vert | D9: Lien vers une autre feuille
B11: PARAMÈTRES DE LA MISSION
B12: TJM retenu (TND / jour) | C12: 700 | D12: Tarif Senior recommandé. Grille : 450 confirmé / 700 senior / 900 expert télécom — justification dans docs/25-chiffrage-mission.md
B13: Taux de TVA | C13: 0.19 | D13: Taux normal en Tunisie 2026. Professions libérales passées de 13 % à 19 %. À confirmer avec un expert-comptable.
B14: Retenue à la source | C14: 0.1 | D14: 10 % en régime réel, 15 % en régime forfaitaire, calculée sur le HT. À confirmer avec un expert-comptable.
B15: Taux de change EUR/TND | C15: 3.373 | D15: Banque Centrale de Tunisie, 15/09/2026. Pour information seulement.
B18: RAPPEL — ce que ce devis ne couvre pas
B19: — Développement de la plateforme Call Com (mission séparée)
B20: — Réalisation du POC technique (le dossier le spécifie, il ne l'exécute pas)
B21: — Conseil juridique et réglementaire (le lot L15 prépare la matière seulement)
B22: — Négociation commerciale avec Orange (partage de revenus, contrat, exclusivité)
B23: — Prospection des annonceurs
B24: — Frais de déplacement hors Grand Tunis (refacturés au réel)
B25: — AUCUNE obligation de résultat sur la décision d'Orange — mission de moyens

Sheet Devis
B2: DEVIS DÉTAILLÉ PAR LIVRABLE
B3: Montants en dinars tunisiens, hors taxes | E3: TJM appliqué : | F3: =Paramètres!C12
B5: Lot | C5: Livrable | D5: Jours | E5: Montant HT | F5: Équiv. EUR | G5: Phase
B6: PHASE 1 — DOSSIER TECHNIQUE (forfait)
B7: L0 | C7: Cadrage et lancement de mission | D7: 1 | E7: =D7*$F$3 | F7: =E7/Paramètres!$C$15 | G7: Ph.1
B8: L1 | C8: Étude de faisabilité télécom — parcours d'appel CS et IMS, composants réseau, déclenchement CAMEL / iFC, budget de latence, variante origine, interconnexion | D8: 5 | E8: =D8*$F$3 | F8: =E8/Paramètres!$C$15 | G8: Ph.1
B9: L2 | C9: Architecture cible — architecture logicielle Call Com, modules, abstraction opérateur, schémas | D9: 4 | E9: =D9*$F$3 | F9: =E9/Paramètres!$C$15 | G9: Ph.1
B10: L3 | C10: Scénarios d'intégration Orange — 3 architectures comparées, trajectoire recommandée | D10: 3 | E10: =D10*$F$3 | F10: =E10/Paramètres!$C$15 | G10: Ph.1
B11: L4 | C11: Flux techniques et contrats d'API — séquences, idempotence, délais de garde, replis, format des remontées | D11: 4 | E11: =D11*$F$3 | F11: =E11/Paramètres!$C$15 | G11: Ph.1
B12: L5 | C12: Sécurité, données personnelles, contraintes — pseudonymat, mTLS, rétention, matrice de conformité | D12: 3 | E12: =D12*$F$3 | F12: =E12/Paramètres!$C$15 | G12: Ph.1
B13: L6 | C13: Proposition de POC — périmètre, matériel, lignes de test, critères chiffrés, métriques, risques | D13: 3 | E13: =D13*$F$3 | F13: =E13/Paramètres!$C$15 | G13: Ph.1
B14: L7 | C14: Questions techniques à adresser à Orange — 7 catégories + checklist de 22 questions | D14: 1.5 | E14: =D14*$F$3 | F14: =E14/Paramètres!$C$15 | G14: Ph.1
B15: L8 | C15: Présentations PowerPoint — pitch 5 minutes + deck technique, avec notes de présentateur | D15: 3 | E15: =D15*$F$3 | F15: =E15/Paramètres!$C$15 | G15: Ph.1
B16: PHASE 2 — ACCOMPAGNEMENT ORANGE (à la journée)
B17: L9 | C17: Présentation technique chez Orange — préparation, répétition, animation (par session) | D17: 2 | E17: =D17*$F$3 | F17: =E17/Paramètres!$C$15 | G17: Ph.2
B18: L10 | C18: Compte rendu de réunion — réponses, décisions, actions, mise à jour du dossier (par réunion) | D18: 1 | E18: =D18*$F$3 | F18: =E18/Paramètres!$C$15 | G18: Ph.2
B19: OPTIONS RECOMMANDÉES
B20: L11 | C20: Note de clôture de la piste applicative — tests sur 6 téléphones, captures, 2 pages | D20: 2 | E20: =D20*$F$3 | F20: =E20/Paramètres!$C$15 | G20: Option
B21: L12 | C21: Dimensionnement des barèmes et plafonds — économie unitaire, CPM plancher | D21: 3 | E21: =D21*$F$3 | F21: =E21/Paramètres!$C$15 | G21: Option
B22: L13 | C22: Schéma de base de données + migrations exécutables + tests | D22: 4 | E22: =D22*$F$3 | F22: =E22/Paramètres!$C$15 | G22: Option
B23: L14 | C23: Registre des risques et plan de mitigation | D23: 1 | E23: =D23*$F$3 | F23: =E23/Paramètres!$C$15 | G23: Option
B24: L15 | C24: Dossier de conformité — matière pour le conseil juridique (INPDP, INT) | D24: 2 | E24: =D24*$F$3 | F24: =E24/Paramètres!$C$15 | G24: Option
C26: Sous-total Phase 1 — dossier technique | D26: =SUM(D7,D8,D9,D10,D11,D12,D13,D14,D15) | E26: =SUM(E7,E8,E9,E10,E11,E12,E13,E14,E15) | F26: =E26/Paramètres!$C$15
C27: Sous-total Phase 2 — par réunion Orange | D27: =SUM(D17,D18) | E27: =SUM(E17,E18) | F27: =E27/Paramètres!$C$15
C28: Sous-total options | D28: =SUM(D20,D21,D22,D23,D24) | E28: =SUM(E20,E21,E22,E23,E24) | F28: =E28/Paramètres!$C$15
C31: Total jours | D31: =D26+D27 | E31: =E26+E27 | F31: =E31/Paramètres!$C$15
C32: Montant hors taxes | E32: =E31 | F32: =E32/Paramètres!$C$15
C33: TVA | E33: =E31*Paramètres!$C$13 | F33: =E33/Paramètres!$C$15
C34: TOTAL TTC FACTURÉ | E34: =E31+E33 | F34: =E34/Paramètres!$C$15
C35: Retenue à la source (acompte d'impôt, sur le HT) | E35: =-E31*Paramètres!$C$14 | F35: =E35/Paramètres!$C$15
C36: ENCAISSÉ À LA FACTURATION | E36: =E34+E35 | F36: =E36/Paramètres!$C$15
B38: ÉCHÉANCIER DE PAIEMENT
C39: À la commande | D39: 0.4 | E39: =D39*$E$32
C40: À la remise du dossier technique | D40: 0.4 | E40: =D40*$E$32
C41: Après la première réunion Orange et son compte rendu | D41: 0.2 | E41: =D41*$E$32
C42: Contrôle — doit faire 100 % | D42: =SUM(D39:D41) | E42: =SUM(E39:E41)
B45: Validité de l'offre : 30 jours · Mission de moyens : aucune obligation de résultat sur la décision d'Orange Tunisie.

Sheet Comparatif formules
B2: COMPARATIF DES FORMULES ET DES TARIFS
B3: Le tarif de la colonne surlignée est celui appliqué dans l'onglet Devis
B5: Formule | C5: Jours | D5: 450 TND/j | E5: 700 TND/j | F5: 900 TND/j
B6: A — Socle « aller chez Orange » | C6: 16.5 | D6: =$C6*450 | E6: =$C6*700 | F6: =$C6*900
B7: B — Dossier technique complet (L0-L8) | C7: 27.5 | D7: =$C7*450 | E7: =$C7*700 | F7: =$C7*900
B8: C — Dossier + 1 réunion Orange (retenue) | C8: 30.5 | D8: =$C8*450 | E8: =$C8*700 | F8: =$C8*900
B9: D — Mission complète (L0-L15) | C9: 42.5 | D9: =$C9*450 | E9: =$C9*700 | F9: =$C9*900
B11: ABONNEMENT D'ACCOMPAGNEMENT (phase Orange)
B12: La durée de cette phase dépend d'Orange, pas de vous : ne jamais la forfaitiser.
B13: 2 jours par mois | C13: 2 | E13: =C13*Paramètres!$C$12
B14: 3 jours par mois | C14: 3 | E14: =C14*Paramètres!$C$12
B15: 4 jours par mois | C15: 4 | E15: =C15*Paramètres!$C$12
B18: REPÈRES DE MARCHÉ 2026 (sources dans docs/25-chiffrage-mission.md)
B19: Freelance développeur, Tunisie | D19: 180 à 500 TND/j
B20: Expert spécialisé, contrats européens | D20: jusqu'à 750 TND/j
B21: Architecte cloud/solution senior, salaire | D21: > 7 000 TND/mois
B22: Coût employeur équivalent | D22: ~500 TND/jour ouvré
B23: Expert IT/logiciel, Europe | D23: 629 € ≈ 2 122 TND/j
B24: Décote nearshore Tunisie vs France | D24: −30 à −50 %
